osmosis_driver_interface/__init__.py
osmosis_driver_interface/computing_plugin.py
osmosis_driver_interface/constants.py
osmosis_driver_interface/data_plugin.py
osmosis_driver_interface/exceptions.py
osmosis_driver_interface/log.py
osmosis_driver_interface/osmosis.py
osmosis_driver_interface/utils.py
osmosis_driver_interface-0.1.0.dist-info/LICENSE
osmosis_driver_interface-0.1.0.dist-info/METADATA
osmosis_driver_interface-0.1.0.dist-info/WHEEL
osmosis_driver_interface-0.1.0.dist-info/top_level.txt
osmosis_driver_interface-0.1.0.dist-info/RECORD
